{
    "Drug Vehicle": "毒品载具",
    "Movie Props": "电影道具",
    "Sleeping Guard": "沉睡的保安",
    "Exotic Exports": "载具出口",
    "Slashers": "屠杀者(玩家对抗)",
    "Phantom Car": "幽灵汽车",
    "Sightseeing": "UFO观光",
    "Smuggler Trail": "走私犯追踪",
    "Cerberus": "地狱犬惊喜",
    "Smuggler Plane": "走私犯飞机",
    "Crime Scene": "犯罪现场",
    "Metal Detector": "金属探测器",
    "Finders Keepers": "先抢先得(产业原材料车队)",
    "Store Robbery": "商店抢劫",
    "Gooch": "古奇",
    "Weazel Bank Shootout": "威泽尔广场枪战",
    "Armored Truck": "装甲运钞车",
    "Possessed Animals": "鬼上身动物",
    "Ghosts Exposed": "幽灵曝光",
    "Happy Holidays Hauler": "圣诞节庆卡车",
    "Random Events": "随机事件",
    " is available.": " 可用.",
    " is available.\\nWarning: Tunable is not active.": " 可用.\n警告: 可调整项未激活.",
    " is triggered by ": " 被触发,玩家: ",
    "Random Events are not initialized.": "随机事件未初始化.",
    "Select Event": "选择事件",
    "Select Location (0-": "选择位置 (0-",
    "Active Events: ": "已激活事件: ",
    "Shows the current number of active events (locally) out of the maximum allowed.": "显示当前活动事件的数量(本地)与最大允许值.",
    "Launch Event": "启动事件",
    "Failed to launch event. Are you freemode host?": "无法启动事件.你是自由模式主机吗?",
    "Event is already active.": "事件已经激活.",
    "Kill Event": "终止事件",
    "Failed to kill event. You must be event host.": "无法终止事件.你必须是事件主机.",
    "Event is not active.": "事件未激活.",
    "Teleport to Event": "传送到事件",
    "Failed to teleport to event. Wait for coordinates to be updated.": "无法传送到事件.请等待坐标更新.",
    "State: ": "状态: ",
    "Inactive - launching in ": "未激活 - 启动于 ",
    "Available - deactivating in ": "可用 - 停用于 ",
    "Active": "激活",
    "Cleanup": "清理",
    "Shows the current state of the event.\\n- Inactive\\n- Available\\n- Active\\n- Cleanup": "显示事件的当前状态.\n- 未激活\n- 可用\n- 激活\n- 清理",
    "Host: ": "主机: ",
    "Take Control": "取得控制",
    "Event script is not active. Are you a participant?": "事件脚本未激活.你是参与者吗?",
    "Location: ": "位置: ",
    "Shows the current location of the event.": "显示事件的当前位置.",
    "N/A": "不可用",
    "Trigger Range: ": "触发范围: ",
    " meters": " 米",
    "Shows the distance required to trigger the event when available.": "显示可用时触发事件所需的距离.",
    "Cooldown: ": "冷却时间: ",
    "Shows the duration that the event will be in the inactive state.": "显示事件处于未激活状态的持续时间.",
    "Availability: ": "可用性持续时间: ",
    "Shows the duration that the event will be in the available state.": "显示事件处于可用状态的持续时间.",
    " minutes": " 分钟",
    "Cooldown & Availability Editor": "冷却时间和可用时间编辑器",
    "Cooldown##cooldown": "冷却时间##cooldown",
    "Apply##apply_cooldown": "应用##apply_cooldown",
    "Failed to set event cooldown. Are you freemode host?": "无法设置事件冷却时间.你是自由模式主机吗?",
    "Availability##availability": "可用性持续时间##availability",
    "Apply##apply_availability": "应用##apply_availability",
    "Failed to set event availability. Are you freemode host?": "无法设置事件可用性持续时间.你是自由模式主机吗?",
    "Apply in Minutes": "使用分钟作为应用单位",
    "Settings": "设置",
    "ESP": "透视",
    "Sphere": "透视事件范围",
    "Line": "透视线",
    "Set Target Player": "设置目标玩家",
    "Allows you to set the target of Phantom Car and Gooch.": "允许你设置幽灵汽车和古奇的目标.",
    "Select Target": "选择目标",
    "Enable Tunables": "启用可调整项(篡改R*云控)",
    "Enables the tunables of special events such as Cerberus, Sightseeing, etc.": "启用特殊事件的可调整项,如地狱犬,观光等.",
    "Bypass Requirements": "绕过触发条件",
    "Bypasses all the requirements to trigger an event such as is tunable enabled, number of players, time of day, etc. Use with caution.": "绕过触发事件的所有要求,如可调整项是否启用,玩家数量,时间等.请谨慎使用.",
    "Disable All Events": "禁用所有事件",
    "Prevents all the events from being triggered.": "阻止所有事件被触发.",
    "Notifications": "通知",
    "Notifies you whenever an event is available or triggered.": "当事件可用或被触发时通知你.",
    "Also Log": "同时输出日志",
    "Force Freemode Host": "强制成为自由模式主机",
    "Forces you to always become freemode host. It is required for script to work correctly.": "强制你始终成为自由模式主机.这对脚本正常工作是必要的.",
    "Challenges": "每日挑战",
    "Hidden Caches": "隐藏的包裹",
    "Treasure Chests": "宝箱",
    "Shipwreck": "沉船",
    "Buried Stashes": "埋藏的藏匿处",
    "Junk Energy Skydives": "拉机能量高空跳伞",
    "Time Trials": "计时赛",
    "G's Cache": "杰拉德的包裹",
    "Stash House": "藏匿屋",
    "Street Dealers": "街头毒贩",
    "LS Tags": "洛圣都海报",
    "Madrazo Hits": "暗杀任务",
    "Daily Reset Time (6 AM UTC)": "每日重置时间 (UTC 6:00)",
    "Reset All Daily Collectibles": "重置所有每日收藏品",
    "Daily Collectibles": "每日收藏品",
    "All Daily Collectibles have been reset.": "已重置所有每日收藏品",
    "Complete All Daily Collectibles": "收集所有每日收藏品",
    "All Daily Collectibles have been completed.": "已完成所有每日收藏品收集",
    "Switch session to apply the changes.": "切换战局以应用更改",
    "Daily Challenges": "每日挑战",
    "Weekly Challenge": "每周挑战",
    "Override: ": "覆盖: ",
    "Complete all Challenges": "完成所有挑战",
    "Status: ": "状态: ",
    "collected": "已收集",
    "ready": "就绪",
    "Select Cache": "选择包裹",
    "Teleport": "传送",
    "Hidden Cache has already been collected.": "隐藏的包裹已经被收集了",
    "Collect": "收集",
    "Draw ESP": "绘制ESP透视",
    "Select Treasure": "选择宝箱",
    "Treasure Chest has already been collected.": "宝厢已经被收集了",
    "Shipwreck has already been collected.": "沉船宝箱已经被收集了",
    "Select Stash": "选择藏匿品",
    "Buried Stash has already been collected.": "埋藏的藏匿品已经被收集了",
    "Challenge Time: ": "挑战时间",
    "Select Skydive": "选择跳伞",
    "Par Time: ": "标准时间",
    "Select Variant": "选择类型",
    "Reward Ready: ": "奖励就绪: ",
    "Yes": "是",
    "No": "否",
    "Teleport to Vehicle": "传送到载具",
    "Please wait until the next vehicle is spawned (90 seconds).": "请等待下一辆载具生成(90秒)",
    "You have already delivered all the vehicles.": "你已经运送了所有载具",
    "Deliver Vehicle": "运送载具",
    "You have just delivered a vehicle. Wait a moment.": "你刚送达了一辆载具. 请稍等",
    "Lose your wanted level.": "消除你的通缉等级",
    "Please get in an Exotic Exports Vehicle.": "请进入一辆异国出口载具",
    "Spawn Next Vehicle": "生成下一辆载具",
    "Today's List:": "今日清单:",
    " (Delivered)": " (已送达)",
    " (Active)": " (可用)",
    "G's Cache has already been collected.": "杰拉德的包裹已经被收集了",
    "Safe Code: ": "保险箱密码: ",
    "unavailable": "不可用",
    "raided": "已抢劫",
    "Enter Safe Combination": "输入保险箱密码",
    "Select Dealer": "选择买家",
    "Weed: $": "大麻: $",
    "Meth: $": "冰毒: $",
    "Cocaine: $": "可卡因: $",
    "Acid: $": "致幻剂: $",
    "Total: $": "总计: $",
    "All: $": "全部: $",
    " unit * ": " 单位 * ",
    "sprayed": "已喷涂",
    "Spray": "喷涂",
    "Spray Can Collected: ": "已拥有喷漆罐: ",
    "Uncollect": "取消收集",
    "Select Tag": "选择海报",
    "LS Tag has already been sprayed.": "洛圣都海报已经被喷涂了",
    "Madrazo Hit has already been completed.": "马德拉所暗杀已完成",
    "Mini-game instant complete": "立即完成小游戏",
    "Gun Van": "枪支厢型车",
    "Weapon Editor": "武器编辑器",
    "Select Slot": "选择槽位",
    "Weapon Name": "武器名称",
    "Set Weapon": "设置武器",
    "Invalid weapon.": "无效的武器。",
    "Remove Weapon": "移除武器",
    "Close": "关闭",
    "Current Location: ": "当前位置：",
    "Set Location": "设置位置",
    "Weapon Skins": "武器外观",
    "Enables the special liveries for Knife and Baseball Bat.": "启用刀和棒球棒的特殊涂装",
    "Blip Always Visible": "始终显示标记",
    "The Gun Van will always be blipped on the map, just like in GTA+.": "枪支厢型车将始终在地图上显示,就像GTA+会员一样。",
    "Weapons": "武器",
    "Edit Weapons": "编辑武器",
    "Throwables": "投掷物",
    "Body Armor": "防弹衣",
    "Super Light Armor (": "超轻型防弹衣（",
    "Light Armor (": "轻型防弹衣（",
    "Standard Armor (": "标准防弹衣（",
    "Heavy Armor (": "重型防弹衣（",
    "Super Heavy Armor (": "超重型防弹衣（"
}